secretfunctions/__init__.py
secretfunctions/secretfunctions.py
secretfunctions-0.0.2.dist-info/METADATA
secretfunctions-0.0.2.dist-info/WHEEL
secretfunctions-0.0.2.dist-info/top_level.txt
secretfunctions-0.0.2.dist-info/RECORD
