Metadata-Version: 2.1
Name: secretfunctions
Version: 0.0.2
Summary: simple library to keep some things private and secret
Author-email: NeuralDevelopment <neutro2@outlook.de>
License: MIT License
Project-URL: Homepage, https://dev.azure.com/neuraldevelopment/secretfunctions
Classifier: Programming Language :: Python :: 3
Classifier: License :: OSI Approved :: MIT License
Classifier: Operating System :: OS Independent
Classifier: Programming Language :: Python :: 3.9
Classifier: Programming Language :: Python :: 3.10
Classifier: Programming Language :: Python :: 3.11
Classifier: Programming Language :: Python :: 3.12
Requires-Python: >=3.9
Requires-Dist: load-dotenv >=0.1.0
Provides-Extra: dev
Provides-Extra: test
